airpine/__init__.py
airpine/airpine_builder.py
airpine/airpine_builder.pyi
airpine/py.typed
airpine-0.2.1.dist-info/METADATA
airpine-0.2.1.dist-info/WHEEL
airpine-0.2.1.dist-info/licenses/LICENSE
airpine-0.2.1.dist-info/RECORD
