Metadata-Version: 2.4
Name: airpine
Version: 0.2.1
Summary: Alpine.js integration for Air framework with excellent DX
Project-URL: Homepage, https://github.com/kentro-tech/airpine
Project-URL: Repository, https://github.com/kentro-tech/airpine
Project-URL: Documentation, https://github.com/kentro-tech/airpine#readme
Author-email: Kentro Tech <info@kentro.tech>
License: MIT
License-File: LICENSE
Keywords: air,alpine,alpinejs,html,htmx,web
Classifier: Development Status :: 3 - Alpha
Classifier: Intended Audience :: Developers
Classifier: License :: OSI Approved :: MIT License
Classifier: Programming Language :: Python :: 3
Classifier: Programming Language :: Python :: 3.11
Classifier: Programming Language :: Python :: 3.12
Classifier: Topic :: Internet :: WWW/HTTP :: Dynamic Content
Classifier: Topic :: Software Development :: Libraries :: Python Modules
Requires-Python: >=3.11
Requires-Dist: air[standard]>=0.30.0
Requires-Dist: fastapi[standard]>=0.121.2
Provides-Extra: dev
Requires-Dist: air>=0.5.0; extra == 'dev'
Requires-Dist: mypy>=1.7.0; extra == 'dev'
Requires-Dist: playwright>=1.40.0; extra == 'dev'
Requires-Dist: pytest-asyncio>=0.23.0; extra == 'dev'
Requires-Dist: pytest>=8.0.0; extra == 'dev'
Requires-Dist: ruff>=0.1.0; extra == 'dev'
Requires-Dist: uvicorn; extra == 'dev'
